motiv/__init__.py
motiv/version.py
motiv/actor/__init__.py
motiv/actor/group.py
motiv/actor/process.py
motiv/channel/__init__.py
motiv/channel/mixin.py
motiv/channel/zeromq.py
motiv/exceptions/__init__.py
motiv/proto/__init__.py
motiv/proto/zeromq.py
motiv/serde/__init__.py
motiv/serde/serializable.py
motiv/streams/__init__.py
motiv/streams/mixin.py
motiv/streams/zeromq.py
motiv/sync/__init__.py
motiv/sync/event.py
motiv/sync/mixin.py
motiv-0.1.0.dist-info/LICENSE
motiv-0.1.0.dist-info/METADATA
motiv-0.1.0.dist-info/WHEEL
motiv-0.1.0.dist-info/top_level.txt
motiv-0.1.0.dist-info/RECORD
