Metadata-Version: 2.1
Name: motiv
Version: 0.1.0
Summary: Motiv, Simple and Efficient processing pipelining.
Home-page: https://saadtalaat.com
Author: Saad Talaat
Author-email: saadtalaat@gmail.com
License: UNKNOWN
Platform: POSIX
Classifier: Operating System :: OS Independent
Classifier: Natural Language :: English
Classifier: Intended Audience :: Developers
Classifier: Intended Audience :: Financial and Insurance Industry
Classifier: Programming Language :: Python :: 3
Requires-Dist: pyzmq (==18.0.0)
Requires-Dist: ensure (==0.8.2)
